Metadata-Version: 2.4
Name: voicerun-cli
Version: 0.2.7
Summary: VoiceRun command-line interface
Author-email: VoiceRun <support@voicerun.com>
Requires-Python: >=3.10
Requires-Dist: black>=23.3.0
Requires-Dist: requests>=2.32.4
Requires-Dist: typer>=0.16.0
Requires-Dist: websocket-client>=1.6.0
Requires-Dist: websockets>=11.0.0
Requires-Dist: rich>=13.0.0
Requires-Dist: aiohttp>=3.8.6
Requires-Dist: loguru>=0.7.3
Requires-Dist: pyaudio>=0.2.11
Requires-Dist: numpy>=1.24.0
Requires-Dist: pygame-ce>=2.5.0
Requires-Dist: primfunctions>=0.1.13
Requires-Dist: g711>=1.6.5
Requires-Dist: pygame>=2.6.1
Requires-Dist: six>=1.17.0
Provides-Extra: test
Requires-Dist: pytest>=7.0.0; extra == "test"
Requires-Dist: pytest-mock>=3.10.0; extra == "test"
Requires-Dist: pytest-cov>=4.0.0; extra == "test"
Requires-Dist: pytest-asyncio>=0.21.0; extra == "test"
